pylsp_inlay_hints-0.1.0.dist-info/METADATA
pylsp_inlay_hints-0.1.0.dist-info/WHEEL
pylsp_inlay_hints-0.1.0.dist-info/entry_points.txt
pylsp_inlay_hints-0.1.0.dist-info/licenses/AUTHORS.txt
pylsp_inlay_hints-0.1.0.dist-info/licenses/LICENSE
pylsp_inlay_hints/__init__.py
pylsp_inlay_hints/dispatcher.py
pylsp_inlay_hints/extractor.py
pylsp_inlay_hints/interfaces.py
pylsp_inlay_hints/plugin.py
pylsp_inlay_hints-0.1.0.dist-info/RECORD
