Metadata-Version: 2.1
Name: pylsp-inlay-hints
Version: 0.1.0
Summary: Experimental support for inlay hints provider for `python-lsp-server`
Author-Email: Marcin Paliwoda <boringstuffinc@gmail.com>
License: MIT
Requires-Python: >=3.8
Requires-Dist: astroid>=3.1.0
Requires-Dist: astypes>=0.2.6
Requires-Dist: python-lsp-server>=1.10.1
Requires-Dist: python-lsp-jsonrpc>=1.1.2
Requires-Dist: mypy>=1.9.0; extra == "dev"
Requires-Dist: ruff>=0.3.4; extra == "dev"
Provides-Extra: dev
